ldt/__init__.py
ldt/_version.py
ldt/load_config.py
ldt/dicts/__init__.py
ldt/dicts/dictionary.py
ldt/dicts/normalize.py
ldt/dicts/resources.py
ldt/dicts/base/__init__.py
ldt/dicts/base/babelnet.py
ldt/dicts/base/wiktionary.py
ldt/dicts/base/custom/__init__.py
ldt/dicts/base/custom/en.py
ldt/dicts/base/wordnet/__init__.py
ldt/dicts/base/wordnet/en.py
ldt/dicts/derivation/__init__.py
ldt/dicts/derivation/meta.py
ldt/dicts/derivation/wiktionary.py
ldt/dicts/derivation/custom/__init__.py
ldt/dicts/derivation/custom/affixes.py
ldt/dicts/derivation/custom/compounds.py
ldt/dicts/derivation/custom/custom_dict.py
ldt/dicts/derivation/custom/en/__init__.py
ldt/dicts/derivation/custom/en/en.py
ldt/dicts/derivation/custom/en/en.yaml
ldt/dicts/derivation/wordnet/__init__.py
ldt/dicts/derivation/wordnet/en.py
ldt/dicts/morphology/__init__.py
ldt/dicts/morphology/babelnet.py
ldt/dicts/morphology/meta.py
ldt/dicts/morphology/morph_dictionary.py
ldt/dicts/morphology/wiktionary.py
ldt/dicts/morphology/custom/__init__.py
ldt/dicts/morphology/custom/en.py
ldt/dicts/morphology/wordnet/__init__.py
ldt/dicts/morphology/wordnet/en.py
ldt/dicts/morphology/wordnet/en.vocab
ldt/dicts/semantics/__init__.py
ldt/dicts/semantics/babelnet.py
ldt/dicts/semantics/lex_dictionary.py
ldt/dicts/semantics/metadictionary.py
ldt/dicts/semantics/wikisaurus.py
ldt/dicts/semantics/wiktionary.py
ldt/dicts/semantics/wordnet/__init__.py
ldt/dicts/semantics/wordnet/en.py
ldt/dicts/spellcheck/__init__.py
ldt/dicts/spellcheck/custom.py
ldt/dicts/spellcheck/en/__init__.py
ldt/dicts/spellcheck/en/en.py
ldt/experiments/__init__.py
ldt/experiments/analyze.py
ldt/experiments/annotate.py
ldt/experiments/demo.py
ldt/experiments/metadata.py
ldt/experiments/neighbors.py
ldt/experiments/default_workflow/__init__.py
ldt/experiments/default_workflow/__main__.py
ldt/experiments/default_workflow/default_workflow.py
ldt/helpers/__init__.py
ldt/helpers/exceptions.py
ldt-0.4.0.dist-info/METADATA
ldt-0.4.0.dist-info/RECORD
ldt-0.4.0.dist-info/WHEEL
ldt-0.4.0.dist-info/top_level.txt
