Metadata-Version: 2.1
Name: ldt
Version: 0.4.0
Summary: Linguistic diagnostics for word embeddings
Home-page: http://ldtoolkit.space/
Author: Anna Rogers
Author-email: anna_rogers@uml.edu
License: Apache Software License
Platform: any
Classifier: Programming Language :: Python
Classifier: Natural Language :: English
Classifier: Intended Audience :: Science/Research
Classifier: License :: OSI Approved :: Apache Software License
Classifier: Operating System :: OS Independent
Classifier: Topic :: Text Processing :: Linguistic
Provides-Extra: testing
Requires-Dist: hurry.filesize
Requires-Dist: inflect
Requires-Dist: nltk
Requires-Dist: outdated
Requires-Dist: p-tqdm
Requires-Dist: pandas
Requires-Dist: pyenchant
Requires-Dist: ruamel.yaml
Requires-Dist: timeout-decorator
Requires-Dist: vecto
Requires-Dist: wiktionaryparser (==0.0.7)
Provides-Extra: testing
Requires-Dist: pytest; extra == 'testing'
